pydes/__init__.py
pydes/components.py
pydes/core.py
pydes/monitor.py
py_des_lib-0.1.5.dist-info/LICENSE.txt
py_des_lib-0.1.5.dist-info/METADATA
py_des_lib-0.1.5.dist-info/WHEEL
py_des_lib-0.1.5.dist-info/RECORD
