Metadata-Version: 2.1
Name: py-des-lib
Version: 0.1.5
Summary: Event discrete, process based simulation for Python.
License: MIT
Author: vitostamatti
Author-email: vitostamatti@gmail.com
Requires-Python: >=3.10,<4.0
Classifier: License :: OSI Approved :: MIT License
Classifier: Programming Language :: Python :: 3
Classifier: Programming Language :: Python :: 3.10
Classifier: Programming Language :: Python :: 3.11
Classifier: Programming Language :: Python :: 3.12
Classifier: Programming Language :: Python :: 3.13
Requires-Dist: greenlet (>=3.0.3,<4.0.0)
